ASvid/ASvid.py
ASvid/__init__.py
ASvid-0.0.1.dist-info/METADATA
ASvid-0.0.1.dist-info/WHEEL
ASvid-0.0.1.dist-info/top_level.txt
ASvid-0.0.1.dist-info/RECORD
